CHANGES.rst
MANIFEST.in
README.rst
setup.py
collective/__init__.py
collective.rooter.egg-info/PKG-INFO
collective.rooter.egg-info/SOURCES.txt
collective.rooter.egg-info/dependency_links.txt
collective.rooter.egg-info/entry_points.txt
collective.rooter.egg-info/namespace_packages.txt
collective.rooter.egg-info/not-zip-safe
collective.rooter.egg-info/requires.txt
collective.rooter.egg-info/top_level.txt
collective/rooter/__init__.py
collective/rooter/catalog.py
collective/rooter/configure.zcml
collective/rooter/navroot.py
collective/rooter/subscribers.py
collective/rooter/tests.py
docs/INSTALL.txt
docs/LICENSE.GPL
docs/LICENSE.txt