Metadata-Version: 1.1
Name: collective.rooter
Version: 1.0
Summary: Tools to force catalog queries to obey the current navigation root
Home-page: http://pypi.python.org/pypi/collective.rooter
Author: Martin Aspeli
Author-email: optilude@gmail.com
License: GPL
Keywords: plone navigation root
Platform: UNKNOWN
Classifier: Framework :: Plone
Classifier: Programming Language :: Python
Classifier: Topic :: Software Development :: Libraries :: Python Modules
